pyownet/__init__.py
pyownet/legacy.py
pyownet/protocol.py
pyownet-0.10.0.post1.dist-info/LICENSE.txt
pyownet-0.10.0.post1.dist-info/METADATA
pyownet-0.10.0.post1.dist-info/WHEEL
pyownet-0.10.0.post1.dist-info/top_level.txt
pyownet-0.10.0.post1.dist-info/RECORD
