Metadata-Version: 2.1
Name: pyownet
Version: 0.10.0.post1
Summary: Python OWFS client library (owserver protocol)
Home-page: https://github.com/miccoli/pyownet
Author: Stefano Miccoli
Author-email: stefano.miccoli@polimi.it
License: LGPLv3
Keywords: OWFS
Platform: UNKNOWN
Classifier: Development Status :: 3 - Alpha
Classifier: Environment :: Other Environment
Classifier: Intended Audience :: Developers
Classifier: License :: OSI Approved :: GNU Lesser General Public License v3 or later (LGPLv3+)
Classifier: Programming Language :: Python
Classifier: Programming Language :: Python :: 2.7
Classifier: Programming Language :: Python :: 3
Classifier: Programming Language :: Python :: 3.3
Classifier: Programming Language :: Python :: 3.4
Classifier: Programming Language :: Python :: 3.5
Classifier: Programming Language :: Python :: 3.6
Classifier: Programming Language :: Python :: 3.7
Classifier: Topic :: Home Automation
